com/__init__.py
com/vmware/__init__.py
com/vmware/vmc_client.py
com/vmware/vmc/__init__.py
com/vmware/vmc/customer_support_client.py
com/vmware/vmc/model_client.py
com/vmware/vmc/orgs_client.py
com/vmware/vmc/orgs/__init__.py
com/vmware/vmc/orgs/account_link_client.py
com/vmware/vmc/orgs/reservations_client.py
com/vmware/vmc/orgs/sddcs_client.py
com/vmware/vmc/orgs/storage_client.py
com/vmware/vmc/orgs/subscriptions_client.py
com/vmware/vmc/orgs/tbrs_client.py
com/vmware/vmc/orgs/aws/__init__.py
com/vmware/vmc/orgs/aws/resources/__init__.py
com/vmware/vmc/orgs/aws/resources/servicequotas_client.py
com/vmware/vmc/orgs/sddcs/__init__.py
com/vmware/vmc/orgs/sddcs/addons_client.py
com/vmware/vmc/orgs/sddcs/clusters_client.py
com/vmware/vmc/orgs/sddcs/dns_client.py
com/vmware/vmc/orgs/sddcs/management_vms_client.py
com/vmware/vmc/orgs/sddcs/networking_client.py
com/vmware/vmc/orgs/sddcs/clusters/__init__.py
com/vmware/vmc/orgs/sddcs/clusters/config_client.py
com/vmware/vmc/orgs/sddcs/clusters/msft_licensing_client.py
oab_vmwarecloud_aws-1.64.0.dist-info/licenses/LICENSE
vmware/__init__.py
vmware/vapi/__init__.py
vmware/vapi/vmc/__init__.py
vmware/vapi/vmc/client.py
vmware/vapi/vmc/csp_filter.py
oab_vmwarecloud_aws-1.64.0.dist-info/METADATA
oab_vmwarecloud_aws-1.64.0.dist-info/WHEEL
oab_vmwarecloud_aws-1.64.0.dist-info/top_level.txt
oab_vmwarecloud_aws-1.64.0.dist-info/RECORD
